{
"meta":{"test_sets":[],"test_metrics":[],"learn_metrics":[{"best_value":"Min","name":"Logloss"}],"launch_mode":"Train","parameters":"","iteration_count":687,"learn_sets":["learn"],"name":"experiment"},
"iterations":[
{"learn":[0.6385109798],"iteration":0,"passed_time":0.5714218893,"remaining_time":391.9954161},
{"learn":[0.586901082],"iteration":1,"passed_time":0.853429313,"remaining_time":292.2995397},
{"learn":[0.5441751201],"iteration":2,"passed_time":1.199727595,"remaining_time":273.5378917},
{"learn":[0.5054003775],"iteration":3,"passed_time":1.525072404,"remaining_time":260.4061129},
{"learn":[0.4566726982],"iteration":4,"passed_time":1.88408577,"remaining_time":256.9892991},
{"learn":[0.4211670261],"iteration":5,"passed_time":2.17312665,"remaining_time":246.6498748},
{"learn":[0.3964792224],"iteration":6,"passed_time":2.448408271,"remaining_time":237.8453749},
{"learn":[0.3714704047],"iteration":7,"passed_time":2.662118057,"remaining_time":225.9472701},
{"learn":[0.3477871181],"iteration":8,"passed_time":2.899748679,"remaining_time":218.4477338},
{"learn":[0.3281142829],"iteration":9,"passed_time":3.120338667,"remaining_time":211.2469277},
{"learn":[0.3132336252],"iteration":10,"passed_time":3.345770077,"remaining_time":205.6127793},
{"learn":[0.2981352846],"iteration":11,"passed_time":3.612899748,"remaining_time":203.2256108},
{"learn":[0.2885884544],"iteration":12,"passed_time":4.035888246,"remaining_time":209.2452829},
{"learn":[0.276313961],"iteration":13,"passed_time":4.275353686,"remaining_time":205.5223594},
{"learn":[0.2643854197],"iteration":14,"passed_time":4.487331919,"remaining_time":201.03247},
{"learn":[0.2567447801],"iteration":15,"passed_time":4.668940298,"remaining_time":195.8036838},
{"learn":[0.2390839161],"iteration":16,"passed_time":5.002620178,"remaining_time":197.1620894},
{"learn":[0.2247858546],"iteration":17,"passed_time":5.20562518,"remaining_time":193.4757358},
{"learn":[0.2144609585],"iteration":18,"passed_time":5.384848455,"remaining_time":189.3199352},
{"learn":[0.2083640766],"iteration":19,"passed_time":5.604889801,"remaining_time":186.9230749},
{"learn":[0.201238287],"iteration":20,"passed_time":5.968313035,"remaining_time":189.2807848},
{"learn":[0.1909664782],"iteration":21,"passed_time":6.145458688,"remaining_time":185.7604558},
{"learn":[0.1811520674],"iteration":22,"passed_time":6.393072803,"remaining_time":184.5652322},
{"learn":[0.1713303394],"iteration":23,"passed_time":6.673561916,"remaining_time":184.3571479},
{"learn":[0.1667860319],"iteration":24,"passed_time":7.068947569,"remaining_time":187.1857316},
{"learn":[0.1606073178],"iteration":25,"passed_time":7.417426176,"remaining_time":188.5737963},
{"learn":[0.1525036319],"iteration":26,"passed_time":7.632062631,"remaining_time":186.561531},
{"learn":[0.148206499],"iteration":27,"passed_time":7.853483948,"remaining_time":184.8373543},
{"learn":[0.1401089055],"iteration":28,"passed_time":8.081429561,"remaining_time":183.36485},
{"learn":[0.1349951297],"iteration":29,"passed_time":8.294345982,"remaining_time":181.646177},
{"learn":[0.1310563377],"iteration":30,"passed_time":8.554366453,"remaining_time":181.021432},
{"learn":[0.1285514804],"iteration":31,"passed_time":8.817087468,"remaining_time":180.4747591},
{"learn":[0.1249772473],"iteration":32,"passed_time":9.042328143,"remaining_time":179.2025032},
{"learn":[0.121841026],"iteration":33,"passed_time":9.350405555,"remaining_time":179.582789},
{"learn":[0.1194367696],"iteration":34,"passed_time":9.584599883,"remaining_time":178.5474035},
{"learn":[0.116198008],"iteration":35,"passed_time":9.823276564,"remaining_time":177.6375845},
{"learn":[0.1134832637],"iteration":36,"passed_time":10.03661877,"remaining_time":176.3189783},
{"learn":[0.1093478659],"iteration":37,"passed_time":10.17634204,"remaining_time":173.80121},
{"learn":[0.1048791499],"iteration":38,"passed_time":10.30155193,"remaining_time":171.1642475},
{"learn":[0.09777953068],"iteration":39,"passed_time":10.43545031,"remaining_time":168.7934088},
{"learn":[0.09485543978],"iteration":40,"passed_time":10.56820177,"remaining_time":166.5136181},
{"learn":[0.09132458456],"iteration":41,"passed_time":10.78353656,"remaining_time":165.6043114},
{"learn":[0.08650606171],"iteration":42,"passed_time":10.90968369,"remaining_time":163.3915418},
{"learn":[0.08551049981],"iteration":43,"passed_time":11.05585114,"remaining_time":161.5661882},
{"learn":[0.08332553102],"iteration":44,"passed_time":11.18274924,"remaining_time":159.5405558},
{"learn":[0.08068023846],"iteration":45,"passed_time":11.31192526,"remaining_time":157.6292194},
{"learn":[0.07810615334],"iteration":46,"passed_time":11.44492225,"remaining_time":155.8457499},
{"learn":[0.07475198002],"iteration":47,"passed_time":11.57068149,"remaining_time":154.0346974},
{"learn":[0.07137248957],"iteration":48,"passed_time":11.7129647,"remaining_time":152.5075811},
{"learn":[0.0688301743],"iteration":49,"passed_time":11.86323553,"remaining_time":151.1376207},
{"learn":[0.06563746136],"iteration":50,"passed_time":12.05353328,"remaining_time":150.3146503},
{"learn":[0.06347592285],"iteration":51,"passed_time":12.21226617,"remaining_time":149.1305581},
{"learn":[0.06173935236],"iteration":52,"passed_time":12.33755054,"remaining_time":147.5850385},
{"learn":[0.05973326152],"iteration":53,"passed_time":12.47721591,"remaining_time":146.2606977},
{"learn":[0.05786548592],"iteration":54,"passed_time":12.60982509,"remaining_time":144.8983537},
{"learn":[0.05682736131],"iteration":55,"passed_time":12.73927465,"remaining_time":143.5443268},
{"learn":[0.05413087126],"iteration":56,"passed_time":12.87132465,"remaining_time":142.2620093},
{"learn":[0.05287395454],"iteration":57,"passed_time":12.99749693,"remaining_time":140.9556132},
{"learn":[0.05049008563],"iteration":58,"passed_time":13.13259168,"remaining_time":139.7841962},
{"learn":[0.04722637959],"iteration":59,"passed_time":13.26802285,"remaining_time":138.6508387},
{"learn":[0.04584764471],"iteration":60,"passed_time":13.39498226,"remaining_time":137.4632606},
{"learn":[0.04470518639],"iteration":61,"passed_time":13.52612503,"remaining_time":136.3520668},
{"learn":[0.043506796],"iteration":62,"passed_time":13.66188439,"remaining_time":135.3177121},
{"learn":[0.04248986141],"iteration":63,"passed_time":13.80988842,"remaining_time":134.4306326},
{"learn":[0.04071296608],"iteration":64,"passed_time":13.97688263,"remaining_time":133.7480153},
{"learn":[0.0376931708],"iteration":65,"passed_time":14.1803163,"remaining_time":133.4238852},
{"learn":[0.03620915709],"iteration":66,"passed_time":14.30903015,"remaining_time":132.4119208},
{"learn":[0.03424615332],"iteration":67,"passed_time":14.46785916,"remaining_time":131.7000709},
{"learn":[0.0333997663],"iteration":68,"passed_time":14.59863757,"remaining_time":130.7530148},
{"learn":[0.03276875238],"iteration":69,"passed_time":14.72897509,"remaining_time":129.8253947},
{"learn":[0.03127666097],"iteration":70,"passed_time":14.89474187,"remaining_time":129.2276196},
{"learn":[0.02895654986],"iteration":71,"passed_time":15.05435003,"remaining_time":128.5892398},
{"learn":[0.02781238374],"iteration":72,"passed_time":15.20721923,"remaining_time":127.907296},
{"learn":[0.02643123525],"iteration":73,"passed_time":15.34684651,"remaining_time":127.1299583},
{"learn":[0.02482009202],"iteration":74,"passed_time":15.50070043,"remaining_time":126.4857155},
{"learn":[0.0240800345],"iteration":75,"passed_time":15.62497169,"remaining_time":125.6165487},
{"learn":[0.02298113991],"iteration":76,"passed_time":15.77525067,"remaining_time":124.9727651},
{"learn":[0.02236351917],"iteration":77,"passed_time":15.94664265,"remaining_time":124.5064792},
{"learn":[0.021228355],"iteration":78,"passed_time":16.15592306,"remaining_time":124.3392559},
{"learn":[0.02025676166],"iteration":79,"passed_time":16.29550829,"remaining_time":123.6421692},
{"learn":[0.01909958683],"iteration":80,"passed_time":16.42923599,"remaining_time":122.9150248},
{"learn":[0.01802821006],"iteration":81,"passed_time":16.55933387,"remaining_time":122.1755731},
{"learn":[0.01743512681],"iteration":82,"passed_time":16.71755407,"remaining_time":121.6554537},
{"learn":[0.01634885735],"iteration":83,"passed_time":16.85553747,"remaining_time":120.9986797},
{"learn":[0.01584855995],"iteration":84,"passed_time":16.97865592,"remaining_time":120.2488337},
{"learn":[0.01552654222],"iteration":85,"passed_time":17.18164438,"remaining_time":120.0717241},
{"learn":[0.01514402984],"iteration":86,"passed_time":17.41464779,"remaining_time":120.1010192},
{"learn":[0.01446406486],"iteration":87,"passed_time":17.53945776,"remaining_time":119.3879},
{"learn":[0.01410770202],"iteration":88,"passed_time":17.67768618,"remaining_time":118.778161},
{"learn":[0.01359259503],"iteration":89,"passed_time":17.81120122,"remaining_time":118.1476347},
{"learn":[0.01310792215],"iteration":90,"passed_time":17.93589623,"remaining_time":117.4702654},
{"learn":[0.01269890536],"iteration":91,"passed_time":18.06691177,"remaining_time":116.8457881},
{"learn":[0.01214619261],"iteration":92,"passed_time":18.20545229,"remaining_time":116.2799856},
{"learn":[0.01155094237],"iteration":93,"passed_time":18.3398805,"remaining_time":115.6973312},
{"learn":[0.01107379761],"iteration":94,"passed_time":18.47532551,"remaining_time":115.1304495},
{"learn":[0.0107160096],"iteration":95,"passed_time":18.61152814,"remaining_time":114.5772201},
{"learn":[0.01023091999],"iteration":96,"passed_time":18.74577775,"remaining_time":114.02071},
{"learn":[0.00999070694],"iteration":97,"passed_time":18.87466328,"remaining_time":113.4405783},
{"learn":[0.009715909822],"iteration":98,"passed_time":19.00912266,"remaining_time":112.9026679},
{"learn":[0.009393849655],"iteration":99,"passed_time":19.14032442,"remaining_time":112.3537043},
{"learn":[0.008995888567],"iteration":100,"passed_time":19.27853446,"remaining_time":111.8536752},
{"learn":[0.008722886454],"iteration":101,"passed_time":19.40824229,"remaining_time":111.3119778},
{"learn":[0.008216407822],"iteration":102,"passed_time":19.53783955,"remaining_time":110.7776534},
{"learn":[0.007989481838],"iteration":103,"passed_time":19.66759009,"remaining_time":110.2519714},
{"learn":[0.007717048221],"iteration":104,"passed_time":19.80362176,"remaining_time":109.7686463},
{"learn":[0.007443715854],"iteration":105,"passed_time":19.93183566,"remaining_time":109.2490237},
{"learn":[0.00708263582],"iteration":106,"passed_time":20.0617654,"remaining_time":108.746018},
{"learn":[0.006893018867],"iteration":107,"passed_time":20.19450576,"remaining_time":108.2649892},
{"learn":[0.006666775684],"iteration":108,"passed_time":20.32856721,"remaining_time":107.7973564},
{"learn":[0.006341247837],"iteration":109,"passed_time":20.49787285,"remaining_time":107.5206603},
{"learn":[0.005970998584],"iteration":110,"passed_time":20.71718849,"remaining_time":107.5054106},
{"learn":[0.005663342501],"iteration":111,"passed_time":20.86920559,"remaining_time":107.1410109},
{"learn":[0.005490009519],"iteration":112,"passed_time":21.03069292,"remaining_time":106.8284755},
{"learn":[0.005302405661],"iteration":113,"passed_time":21.16565942,"remaining_time":106.3852881},
{"learn":[0.005173974904],"iteration":114,"passed_time":21.30294054,"remaining_time":105.9589738},
{"learn":[0.005016210816],"iteration":115,"passed_time":21.43088561,"remaining_time":105.4916869},
{"learn":[0.004879363544],"iteration":116,"passed_time":21.55842915,"remaining_time":105.0282446},
{"learn":[0.004651372791],"iteration":117,"passed_time":21.68971525,"remaining_time":104.5885422},
{"learn":[0.004451110814],"iteration":118,"passed_time":21.82653398,"remaining_time":104.1804311},
{"learn":[0.004208892874],"iteration":119,"passed_time":21.95947046,"remaining_time":103.7584979},
{"learn":[0.004096511058],"iteration":120,"passed_time":22.09176902,"remaining_time":103.3383576},
{"learn":[0.003991792518],"iteration":121,"passed_time":22.27045552,"remaining_time":103.1377653},
{"learn":[0.003861730635],"iteration":122,"passed_time":22.42872074,"remaining_time":102.8438902},
{"learn":[0.003751765817],"iteration":123,"passed_time":22.56546988,"remaining_time":102.4545124},
{"learn":[0.003638376651],"iteration":124,"passed_time":22.69989382,"remaining_time":102.0587226},
{"learn":[0.003459891902],"iteration":125,"passed_time":22.83482642,"remaining_time":101.6693462},
{"learn":[0.003345352015],"iteration":126,"passed_time":22.96882305,"remaining_time":101.2798497},
{"learn":[0.003271420143],"iteration":127,"passed_time":23.10491964,"remaining_time":100.9035163},
{"learn":[0.003103340216],"iteration":128,"passed_time":23.22996187,"remaining_time":100.4830909},
{"learn":[0.002957953565],"iteration":129,"passed_time":23.3755335,"remaining_time":100.1551705},
{"learn":[0.002861425782],"iteration":130,"passed_time":23.50550544,"remaining_time":99.76382463},
{"learn":[0.002707896165],"iteration":131,"passed_time":23.63560707,"remaining_time":99.37698425},
{"learn":[0.002670257949],"iteration":132,"passed_time":23.76237629,"remaining_time":98.98012379},
{"learn":[0.002600941269],"iteration":133,"passed_time":23.89796274,"remaining_time":98.62368206},
{"learn":[0.002499602317],"iteration":134,"passed_time":24.11312627,"remaining_time":98.59589407},
{"learn":[0.002430857699],"iteration":135,"passed_time":24.23463316,"remaining_time":98.18590348},
{"learn":[0.00231525964],"iteration":136,"passed_time":24.37736701,"remaining_time":97.86534203},
{"learn":[0.002242232225],"iteration":137,"passed_time":24.50893866,"remaining_time":97.50295161},
{"learn":[0.00217479989],"iteration":138,"passed_time":24.6417724,"remaining_time":97.14885809},
{"learn":[0.002099918089],"iteration":139,"passed_time":24.76972833,"remaining_time":96.77886713},
{"learn":[0.002021056819],"iteration":140,"passed_time":24.90044761,"remaining_time":96.42300988},
{"learn":[0.001992923249],"iteration":141,"passed_time":25.03158515,"remaining_time":96.07192891},
{"learn":[0.001951201959],"iteration":142,"passed_time":25.16252937,"remaining_time":95.72318865},
{"learn":[0.00188550917],"iteration":143,"passed_time":25.30308697,"remaining_time":95.41372376},
{"learn":[0.001786572058],"iteration":144,"passed_time":25.45824547,"remaining_time":95.16116582},
{"learn":[0.001716873944],"iteration":145,"passed_time":25.58901214,"remaining_time":94.81955868},
{"learn":[0.001677017918],"iteration":146,"passed_time":25.71670383,"remaining_time":94.46952428},
{"learn":[0.00161941656],"iteration":147,"passed_time":25.85697228,"remaining_time":94.16829769},
{"learn":[0.001570026288],"iteration":148,"passed_time":26.01562322,"remaining_time":93.93560598},
{"learn":[0.001531230396],"iteration":149,"passed_time":26.16441737,"remaining_time":93.66861419},
{"learn":[0.001490605618],"iteration":150,"passed_time":26.40218171,"remaining_time":93.71900263},
{"learn":[0.001413215517],"iteration":151,"passed_time":26.64029293,"remaining_time":93.76682051},
{"learn":[0.001360144647],"iteration":152,"passed_time":26.76353311,"remaining_time":93.40997829},
{"learn":[0.001302904038],"iteration":153,"passed_time":26.89193867,"remaining_time":93.07404746},
{"learn":[0.001267764046],"iteration":154,"passed_time":27.03233587,"remaining_time":92.7819528},
{"learn":[0.001216253418],"iteration":155,"passed_time":27.16308715,"remaining_time":92.45896974},
{"learn":[0.001173553132],"iteration":156,"passed_time":27.41500847,"remaining_time":92.54748081},
{"learn":[0.001144446628],"iteration":157,"passed_time":27.58314917,"remaining_time":92.35117665},
{"learn":[0.001111145419],"iteration":158,"passed_time":27.77497238,"remaining_time":92.23387053},
{"learn":[0.001075712174],"iteration":159,"passed_time":27.90792861,"remaining_time":91.92173985},
{"learn":[0.001041052675],"iteration":160,"passed_time":28.03377757,"remaining_time":91.58861493},
{"learn":[0.001007309135],"iteration":161,"passed_time":28.16678678,"remaining_time":91.28125347},
{"learn":[0.0009758625801],"iteration":162,"passed_time":28.30081808,"remaining_time":90.97931701},
{"learn":[0.0009398035978],"iteration":163,"passed_time":28.50282447,"remaining_time":90.89620242},
{"learn":[0.000924838686],"iteration":164,"passed_time":28.63197221,"remaining_time":90.58114845},
{"learn":[0.0009063445728],"iteration":165,"passed_time":28.76067895,"remaining_time":90.26695021},
{"learn":[0.0008866523038],"iteration":166,"passed_time":28.8858347,"remaining_time":89.94391643},
{"learn":[0.0008660035073],"iteration":167,"passed_time":29.01234753,"remaining_time":89.62743078},
{"learn":[0.0008503370706],"iteration":168,"passed_time":29.1498149,"remaining_time":89.34676994},
{"learn":[0.0008302198566],"iteration":169,"passed_time":29.27476907,"remaining_time":89.02973888},
{"learn":[0.0008161772341],"iteration":170,"passed_time":29.40326458,"remaining_time":88.72564049},
{"learn":[0.0008017276772],"iteration":171,"passed_time":29.54098468,"remaining_time":88.45120412},
{"learn":[0.0007730297126],"iteration":172,"passed_time":29.67774779,"remaining_time":88.175505},
{"learn":[0.0007585045466],"iteration":173,"passed_time":29.80870958,"remaining_time":87.88429893},
{"learn":[0.0007417370066],"iteration":174,"passed_time":29.94132982,"remaining_time":87.59977639},
{"learn":[0.00072584878],"iteration":175,"passed_time":30.07630963,"remaining_time":87.32383081},
{"learn":[0.0007071240053],"iteration":176,"passed_time":30.20955303,"remaining_time":87.04447483},
{"learn":[0.0006890358458],"iteration":177,"passed_time":30.3404413,"remaining_time":86.76002596},
{"learn":[0.0006716405623],"iteration":178,"passed_time":30.48116752,"remaining_time":86.50521285},
{"learn":[0.0006590115997],"iteration":179,"passed_time":30.60457375,"remaining_time":86.20288274},
{"learn":[0.0006467925584],"iteration":180,"passed_time":30.82272978,"remaining_time":86.16741031},
{"learn":[0.0006467925584],"iteration":181,"passed_time":30.94365725,"remaining_time":85.86014787},
{"learn":[0.0006467925584],"iteration":182,"passed_time":31.08142078,"remaining_time":85.60129002},
{"learn":[0.0006467925584],"iteration":183,"passed_time":31.20891085,"remaining_time":85.31566389},
{"learn":[0.0006338179602],"iteration":184,"passed_time":31.34591151,"remaining_time":85.05755449},
{"learn":[0.0006192841455],"iteration":185,"passed_time":31.48008222,"remaining_time":84.79312469},
{"learn":[0.0006192841455],"iteration":186,"passed_time":31.63679733,"remaining_time":84.5903672},
{"learn":[0.0006192841455],"iteration":187,"passed_time":31.77164958,"remaining_time":84.33006989},
{"learn":[0.0006192841455],"iteration":188,"passed_time":31.91603157,"remaining_time":84.09621016},
{"learn":[0.0006192841455],"iteration":189,"passed_time":32.0394083,"remaining_time":83.80834697},
{"learn":[0.000601090775],"iteration":190,"passed_time":32.19599569,"remaining_time":83.60844955},
{"learn":[0.0005888954953],"iteration":191,"passed_time":32.32597243,"remaining_time":83.34039768},
{"learn":[0.0005888954953],"iteration":192,"passed_time":32.51199665,"remaining_time":83.21723495},
{"learn":[0.0005888954953],"iteration":193,"passed_time":32.66859026,"remaining_time":83.018634},
{"learn":[0.000575873151],"iteration":194,"passed_time":32.79907306,"remaining_time":82.75458433},
{"learn":[0.000575873151],"iteration":195,"passed_time":32.92822759,"remaining_time":82.48857012},
{"learn":[0.000575873151],"iteration":196,"passed_time":33.05362105,"remaining_time":82.21459044},
{"learn":[0.000575873151],"iteration":197,"passed_time":33.18186368,"remaining_time":81.94914818},
{"learn":[0.0005620968547],"iteration":198,"passed_time":33.31685752,"remaining_time":81.70164055},
{"learn":[0.0005439915315],"iteration":199,"passed_time":33.44547045,"remaining_time":81.43972054},
{"learn":[0.0005439915315],"iteration":200,"passed_time":33.58228164,"remaining_time":81.19894964},
{"learn":[0.0005439915315],"iteration":201,"passed_time":33.71412404,"remaining_time":80.94727801},
{"learn":[0.0005439938943],"iteration":202,"passed_time":33.83926797,"remaining_time":80.68081625},
{"learn":[0.0005439938943],"iteration":203,"passed_time":33.99875865,"remaining_time":80.49706091},
{"learn":[0.0005439938943],"iteration":204,"passed_time":34.18778024,"remaining_time":80.38297598},
{"learn":[0.0005439679928],"iteration":205,"passed_time":34.31390301,"remaining_time":80.1212978},
{"learn":[0.0005439679928],"iteration":206,"passed_time":34.45053865,"remaining_time":79.885307},
{"learn":[0.0005439679928],"iteration":207,"passed_time":34.58713123,"remaining_time":79.6501724},
{"learn":[0.0005439679928],"iteration":208,"passed_time":34.71371892,"remaining_time":79.39309876},
{"learn":[0.0005439679928],"iteration":209,"passed_time":34.84950012,"remaining_time":79.15815028},
{"learn":[0.0005439679928],"iteration":210,"passed_time":34.97353017,"remaining_time":78.89763204},
{"learn":[0.0005439679928],"iteration":211,"passed_time":35.10881588,"remaining_time":78.66362049},
{"learn":[0.0005439679928],"iteration":212,"passed_time":35.23912601,"remaining_time":78.41946351},
{"learn":[0.0005439679928],"iteration":213,"passed_time":35.36875514,"remaining_time":78.17486534},
{"learn":[0.0005439679928],"iteration":214,"passed_time":35.49261699,"remaining_time":77.91867543},
{"learn":[0.0005328880822],"iteration":215,"passed_time":35.63475083,"remaining_time":77.70355389},
{"learn":[0.0005328880822],"iteration":216,"passed_time":35.76824872,"remaining_time":77.47040045},
{"learn":[0.0005328880822],"iteration":217,"passed_time":35.89433447,"remaining_time":77.22221498},
{"learn":[0.0005328880822],"iteration":218,"passed_time":36.02436643,"remaining_time":76.98357757},
{"learn":[0.0005328880822],"iteration":219,"passed_time":36.15673308,"remaining_time":76.7508834},
{"learn":[0.0005328880822],"iteration":220,"passed_time":36.28434827,"remaining_time":76.50907825},
{"learn":[0.0005328880822],"iteration":221,"passed_time":36.41306903,"remaining_time":76.27061756},
{"learn":[0.0005328880822],"iteration":222,"passed_time":36.5678869,"remaining_time":76.08744179},
{"learn":[0.0005328880822],"iteration":223,"passed_time":36.7743694,"remaining_time":76.01130817},
{"learn":[0.0005328758671],"iteration":224,"passed_time":36.94728338,"remaining_time":75.86508855},
{"learn":[0.0005328758671],"iteration":225,"passed_time":37.07104197,"remaining_time":75.61836436},
{"learn":[0.0005204276354],"iteration":226,"passed_time":37.25021676,"remaining_time":75.48502075},
{"learn":[0.0005204276354],"iteration":227,"passed_time":37.55038634,"remaining_time":75.59485671},
{"learn":[0.0005204276354],"iteration":228,"passed_time":37.83752281,"remaining_time":75.67504562},
{"learn":[0.0005204276354],"iteration":229,"passed_time":38.06379057,"remaining_time":75.63109691},
{"learn":[0.0005204276354],"iteration":230,"passed_time":38.29382785,"remaining_time":75.59301082},
{"learn":[0.0005204611602],"iteration":231,"passed_time":38.41705331,"remaining_time":75.34378989},
{"learn":[0.0005204611602],"iteration":232,"passed_time":38.5566399,"remaining_time":75.12753011},
{"learn":[0.0005204611602],"iteration":233,"passed_time":38.68756123,"remaining_time":74.89515059},
{"learn":[0.0005204611602],"iteration":234,"passed_time":38.81331313,"remaining_time":74.65369164},
{"learn":[0.0005204611602],"iteration":235,"passed_time":38.94539254,"remaining_time":74.42530523},
{"learn":[0.0005204611602],"iteration":236,"passed_time":39.07894559,"remaining_time":74.2005296},
{"learn":[0.0005204611602],"iteration":237,"passed_time":39.21487357,"remaining_time":73.98100097},
{"learn":[0.0005204611602],"iteration":238,"passed_time":39.34746199,"remaining_time":73.75591202},
{"learn":[0.0005204611602],"iteration":239,"passed_time":39.471188,"remaining_time":73.51508766},
{"learn":[0.0005080283981],"iteration":240,"passed_time":39.6081057,"remaining_time":73.29964789},
{"learn":[0.0005080283981],"iteration":241,"passed_time":39.74587173,"remaining_time":73.08641702},
{"learn":[0.0005080283981],"iteration":242,"passed_time":39.87486551,"remaining_time":72.85777896},
{"learn":[0.0004917602532],"iteration":243,"passed_time":40.01814355,"remaining_time":72.65589178},
{"learn":[0.0004917602532],"iteration":244,"passed_time":40.15199388,"remaining_time":72.43747467},
{"learn":[0.0004917602532],"iteration":245,"passed_time":40.28233219,"remaining_time":72.21344918},
{"learn":[0.0004917602532],"iteration":246,"passed_time":40.40970955,"remaining_time":71.9849077},
{"learn":[0.0004917602532],"iteration":247,"passed_time":40.53995044,"remaining_time":71.76225098},
{"learn":[0.0004917602532],"iteration":248,"passed_time":40.6792149,"remaining_time":71.55620934},
{"learn":[0.0004917602532],"iteration":249,"passed_time":40.85137852,"remaining_time":71.40820965},
{"learn":[0.0004917602532],"iteration":250,"passed_time":41.02204288,"remaining_time":71.25741314},
{"learn":[0.0004774813966],"iteration":251,"passed_time":41.14846879,"remaining_time":71.03009493},
{"learn":[0.0004774813966],"iteration":252,"passed_time":41.28058333,"remaining_time":70.81333267},
{"learn":[0.000477501993],"iteration":253,"passed_time":41.4052701,"remaining_time":70.58457462},
{"learn":[0.000477501993],"iteration":254,"passed_time":41.53921693,"remaining_time":70.37232044},
{"learn":[0.000477501993],"iteration":255,"passed_time":41.67339755,"remaining_time":70.16107166},
{"learn":[0.000477501993],"iteration":256,"passed_time":41.80329821,"remaining_time":69.94326159},
{"learn":[0.000477501993],"iteration":257,"passed_time":41.92633748,"remaining_time":69.71472395},
{"learn":[0.000477501993],"iteration":258,"passed_time":42.06008631,"remaining_time":69.50469861},
{"learn":[0.0004774735949],"iteration":259,"passed_time":42.1867177,"remaining_time":69.283571},
{"learn":[0.0004774735949],"iteration":260,"passed_time":42.31946181,"remaining_time":69.07314456},
{"learn":[0.0004774735949],"iteration":261,"passed_time":42.44433727,"remaining_time":68.8505471},
{"learn":[0.0004774735949],"iteration":262,"passed_time":42.5949039,"remaining_time":68.67011123},
{"learn":[0.0004633333403],"iteration":263,"passed_time":42.78303179,"remaining_time":68.55008502},
{"learn":[0.0004633333403],"iteration":264,"passed_time":42.95598457,"remaining_time":68.4053792},
{"learn":[0.0004633493003],"iteration":265,"passed_time":43.09875716,"remaining_time":68.21269461},
{"learn":[0.0004633493003],"iteration":266,"passed_time":43.22608104,"remaining_time":67.99608253},
{"learn":[0.0004633493003],"iteration":267,"passed_time":43.38627073,"remaining_time":67.83152028},
{"learn":[0.0004633493003],"iteration":268,"passed_time":43.51640702,"remaining_time":67.62029047},
{"learn":[0.0004633493003],"iteration":269,"passed_time":43.64448027,"remaining_time":67.40647509},
{"learn":[0.0004633493003],"iteration":270,"passed_time":43.78298193,"remaining_time":67.20930067},
{"learn":[0.0004633493003],"iteration":271,"passed_time":43.91128956,"remaining_time":66.99700429},
{"learn":[0.0004633493003],"iteration":272,"passed_time":44.03888206,"remaining_time":66.78423874},
{"learn":[0.0004633493003],"iteration":273,"passed_time":44.20936089,"remaining_time":66.63673739},
{"learn":[0.0004633493003],"iteration":274,"passed_time":44.39131557,"remaining_time":66.50626187},
{"learn":[0.0004633493003],"iteration":275,"passed_time":44.51882232,"remaining_time":66.29433323},
{"learn":[0.0004633493003],"iteration":276,"passed_time":44.65226473,"remaining_time":66.09179979},
{"learn":[0.0004633493003],"iteration":277,"passed_time":44.78878638,"remaining_time":65.89429363},
{"learn":[0.0004633493003],"iteration":278,"passed_time":44.91516719,"remaining_time":65.68239503},
{"learn":[0.0004633493003],"iteration":279,"passed_time":45.04172545,"remaining_time":65.4713652},
{"learn":[0.0004633493003],"iteration":280,"passed_time":45.17191617,"remaining_time":65.26618494},
{"learn":[0.0004633493003],"iteration":281,"passed_time":45.30007867,"remaining_time":65.05862363},
{"learn":[0.0004633493003],"iteration":282,"passed_time":45.42664871,"remaining_time":64.84935011},
{"learn":[0.0004633493003],"iteration":283,"passed_time":45.55360162,"remaining_time":64.6412023},
{"learn":[0.0004633225517],"iteration":284,"passed_time":45.67877142,"remaining_time":64.43110916},
{"learn":[0.0004633225517],"iteration":285,"passed_time":45.81956826,"remaining_time":64.24352053},
{"learn":[0.0004633225517],"iteration":286,"passed_time":45.94363796,"remaining_time":64.0329449},
{"learn":[0.0004633225517],"iteration":287,"passed_time":46.07786288,"remaining_time":63.8370392},
{"learn":[0.0004633225517],"iteration":288,"passed_time":46.20865524,"remaining_time":63.63683316},
{"learn":[0.0004633225517],"iteration":289,"passed_time":46.33558815,"remaining_time":63.4318224},
{"learn":[0.0004633225517],"iteration":290,"passed_time":46.46174946,"remaining_time":63.22629824},
{"learn":[0.0004633225517],"iteration":291,"passed_time":46.60180145,"remaining_time":63.04010812},
{"learn":[0.0004633225517],"iteration":292,"passed_time":46.74760649,"remaining_time":62.86196914},
{"learn":[0.0004633294172],"iteration":293,"passed_time":46.89241221,"remaining_time":62.68271429},
{"learn":[0.0004633294172],"iteration":294,"passed_time":47.10901406,"remaining_time":62.59909665},
{"learn":[0.0004633294172],"iteration":295,"passed_time":47.27002257,"remaining_time":62.44114468},
{"learn":[0.0004633294172],"iteration":296,"passed_time":47.40087856,"remaining_time":62.24357791},
{"learn":[0.0004633294172],"iteration":297,"passed_time":47.58750166,"remaining_time":62.11925553},
{"learn":[0.0004633294172],"iteration":298,"passed_time":47.78430657,"remaining_time":62.00772893},
{"learn":[0.0004633294172],"iteration":299,"passed_time":47.95773715,"remaining_time":61.86548093},
{"learn":[0.0004633294172],"iteration":300,"passed_time":48.08934877,"remaining_time":61.66939743},
{"learn":[0.0004633294172],"iteration":301,"passed_time":48.22568524,"remaining_time":61.4797643},
{"learn":[0.0004633294172],"iteration":302,"passed_time":48.37995561,"remaining_time":61.31321107},
{"learn":[0.0004633294172],"iteration":303,"passed_time":48.52895686,"remaining_time":61.14010025},
{"learn":[0.0004633294172],"iteration":304,"passed_time":48.6726443,"remaining_time":60.96049221},
{"learn":[0.0004633294172],"iteration":305,"passed_time":48.81683008,"remaining_time":60.78173941},
{"learn":[0.0004633130114],"iteration":306,"passed_time":48.97981056,"remaining_time":60.62647561},
{"learn":[0.0004633130114],"iteration":307,"passed_time":49.11321188,"remaining_time":60.43476397},
{"learn":[0.0004633130114],"iteration":308,"passed_time":49.24194145,"remaining_time":60.23771479},
{"learn":[0.0004633130114],"iteration":309,"passed_time":49.37954366,"remaining_time":60.05189665},
{"learn":[0.0004633130114],"iteration":310,"passed_time":49.5058834,"remaining_time":59.85277222},
{"learn":[0.0004633130114],"iteration":311,"passed_time":49.63483464,"remaining_time":59.65725318},
{"learn":[0.0004633130114],"iteration":312,"passed_time":49.75828467,"remaining_time":59.45558616},
{"learn":[0.0004633130114],"iteration":313,"passed_time":49.89710765,"remaining_time":59.27267884},
{"learn":[0.0004633130114],"iteration":314,"passed_time":50.02212455,"remaining_time":59.07374709},
{"learn":[0.0004633130114],"iteration":315,"passed_time":50.15915246,"remaining_time":58.88938469},
{"learn":[0.0004633130114],"iteration":316,"passed_time":50.28365373,"remaining_time":58.69069994},
{"learn":[0.0004633130114],"iteration":317,"passed_time":50.40950116,"remaining_time":58.4940438},
{"learn":[0.0004633130114],"iteration":318,"passed_time":50.53655077,"remaining_time":58.29921845},
{"learn":[0.0004633130114],"iteration":319,"passed_time":50.66219238,"remaining_time":58.10320188},
{"learn":[0.0004633130114],"iteration":320,"passed_time":50.79849058,"remaining_time":57.91977431},
{"learn":[0.0004633130114],"iteration":321,"passed_time":51.00957633,"remaining_time":57.82141416},
{"learn":[0.0004633130114],"iteration":322,"passed_time":51.15357641,"remaining_time":57.64675484},
{"learn":[0.0004633130114],"iteration":323,"passed_time":51.2806215,"remaining_time":57.4532889},
{"learn":[0.0004633130114],"iteration":324,"passed_time":51.40563287,"remaining_time":57.25796646},
{"learn":[0.0004633130114],"iteration":325,"passed_time":51.53936325,"remaining_time":57.07273047},
{"learn":[0.0004633130114],"iteration":326,"passed_time":51.66215226,"remaining_time":56.87576396},
{"learn":[0.0004633130114],"iteration":327,"passed_time":51.78782461,"remaining_time":56.6824056},
{"learn":[0.0004633130114],"iteration":328,"passed_time":51.92544887,"remaining_time":56.50246412},
{"learn":[0.0004633130114],"iteration":329,"passed_time":52.05099722,"remaining_time":56.30971517},
{"learn":[0.0004633130114],"iteration":330,"passed_time":52.18277943,"remaining_time":56.12407697},
{"learn":[0.0004633130114],"iteration":331,"passed_time":52.309065,"remaining_time":55.93288577},
{"learn":[0.0004633130114],"iteration":332,"passed_time":52.43983662,"remaining_time":55.74685335},
{"learn":[0.0004633130114],"iteration":333,"passed_time":52.56953273,"remaining_time":55.56001513},
{"learn":[0.0004633007517],"iteration":334,"passed_time":52.72247727,"remaining_time":55.39794626},
{"learn":[0.0004633007517],"iteration":335,"passed_time":52.84609975,"remaining_time":55.20530064},
{"learn":[0.0004633007517],"iteration":336,"passed_time":53.03339227,"remaining_time":55.07919078},
{"learn":[0.0004633007517],"iteration":337,"passed_time":53.17007497,"remaining_time":54.90046203},
{"learn":[0.0004633007517],"iteration":338,"passed_time":53.29987992,"remaining_time":54.71492098},
{"learn":[0.0004633007517],"iteration":339,"passed_time":53.42554274,"remaining_time":54.52548038},
{"learn":[0.0004633007517],"iteration":340,"passed_time":53.55317215,"remaining_time":54.33840927},
{"learn":[0.0004633007517],"iteration":341,"passed_time":53.67734298,"remaining_time":54.14819686},
{"learn":[0.0004633007517],"iteration":342,"passed_time":53.8142455,"remaining_time":53.97113834},
{"learn":[0.0004633007517],"iteration":343,"passed_time":53.97440703,"remaining_time":53.81750468},
{"learn":[0.0004633007517],"iteration":344,"passed_time":54.11460654,"remaining_time":53.64404475},
{"learn":[0.0004633007517],"iteration":345,"passed_time":54.29591931,"remaining_time":53.5112962},
{"learn":[0.0004633007517],"iteration":346,"passed_time":54.51136807,"remaining_time":53.41171511},
{"learn":[0.0004633007517],"iteration":347,"passed_time":54.64048699,"remaining_time":53.22737095},
{"learn":[0.0004633007517],"iteration":348,"passed_time":54.76693272,"remaining_time":53.04075433},
{"learn":[0.0004633007517],"iteration":349,"passed_time":54.90314689,"remaining_time":52.86388715},
{"learn":[0.0004633007517],"iteration":350,"passed_time":55.02946262,"remaining_time":52.67777618},
{"learn":[0.0004633007517],"iteration":351,"passed_time":55.16287619,"remaining_time":52.49876001},
{"learn":[0.0004633007517],"iteration":352,"passed_time":55.28997914,"remaining_time":52.31403125},
{"learn":[0.0004633007517],"iteration":353,"passed_time":55.41712652,"remaining_time":52.12966986},
{"learn":[0.0004633007517],"iteration":354,"passed_time":55.5429635,"remaining_time":51.9444053},
{"learn":[0.0004633007517],"iteration":355,"passed_time":55.6751012,"remaining_time":51.76533286},
{"learn":[0.0004633007517],"iteration":356,"passed_time":55.80760625,"remaining_time":51.58686292},
{"learn":[0.0004633007517],"iteration":357,"passed_time":55.94345758,"remaining_time":51.41172498},
{"learn":[0.0004632834543],"iteration":358,"passed_time":56.06823684,"remaining_time":51.22668993},
{"learn":[0.0004632814927],"iteration":359,"passed_time":56.20517642,"remaining_time":51.05303525},
{"learn":[0.0004632814927],"iteration":360,"passed_time":56.33290767,"remaining_time":50.87126843},
{"learn":[0.0004632814927],"iteration":361,"passed_time":56.46391022,"remaining_time":50.69273708},
{"learn":[0.0004632814927],"iteration":362,"passed_time":56.5903735,"remaining_time":50.51041601},
{"learn":[0.0004632814927],"iteration":363,"passed_time":56.73826901,"remaining_time":50.34742003},
{"learn":[0.0004632814927],"iteration":364,"passed_time":56.86280159,"remaining_time":50.1638962},
{"learn":[0.0004632814927],"iteration":365,"passed_time":56.99911816,"remaining_time":49.99102986},
{"learn":[0.0004632814927],"iteration":366,"passed_time":57.12604673,"remaining_time":49.81017699},
{"learn":[0.0004632814927],"iteration":367,"passed_time":57.30194357,"remaining_time":49.67206521},
{"learn":[0.0004632814927],"iteration":368,"passed_time":57.50394408,"remaining_time":49.5562445},
{"learn":[0.0004632814927],"iteration":369,"passed_time":57.65257083,"remaining_time":49.3942296},
{"learn":[0.0004632814927],"iteration":370,"passed_time":57.89488556,"remaining_time":49.31208581},
{"learn":[0.0004477306989],"iteration":371,"passed_time":58.04186451,"remaining_time":49.14835301},
{"learn":[0.0004477306989],"iteration":372,"passed_time":58.27288712,"remaining_time":49.05545993},
{"learn":[0.0004477306989],"iteration":373,"passed_time":58.43077294,"remaining_time":48.90062014},
{"learn":[0.0004477306989],"iteration":374,"passed_time":58.56048634,"remaining_time":48.72232463},
{"learn":[0.0004477306989],"iteration":375,"passed_time":58.68570169,"remaining_time":48.54056709},
{"learn":[0.0004477306989],"iteration":376,"passed_time":58.81226669,"remaining_time":48.36021929},
{"learn":[0.0004477306989],"iteration":377,"passed_time":58.93830121,"remaining_time":48.17972242},
{"learn":[0.0004477434044],"iteration":378,"passed_time":59.07158624,"remaining_time":48.00540518},
{"learn":[0.0004477434044],"iteration":379,"passed_time":59.20751753,"remaining_time":47.83344179},
{"learn":[0.0004477434044],"iteration":380,"passed_time":59.33815534,"remaining_time":47.6574161},
{"learn":[0.0004477434044],"iteration":381,"passed_time":59.4744537,"remaining_time":47.48614759},
{"learn":[0.0004477434044],"iteration":382,"passed_time":59.63055898,"remaining_time":47.33078311},
{"learn":[0.0004477434044],"iteration":383,"passed_time":59.76225416,"remaining_time":47.15615368},
{"learn":[0.0004477434044],"iteration":384,"passed_time":59.91282894,"remaining_time":46.99655672},
{"learn":[0.0004477434044],"iteration":385,"passed_time":60.07396714,"remaining_time":46.84524381},
{"learn":[0.0004477434044],"iteration":386,"passed_time":60.21145914,"remaining_time":46.67554972},
{"learn":[0.0004477434044],"iteration":387,"passed_time":60.33835673,"remaining_time":46.49785737},
{"learn":[0.0004477434044],"iteration":388,"passed_time":60.47330615,"remaining_time":46.32659443},
{"learn":[0.0004477434044],"iteration":389,"passed_time":60.62538999,"remaining_time":46.16856622},
{"learn":[0.0004477434044],"iteration":390,"passed_time":60.84196896,"remaining_time":46.05939338},
{"learn":[0.0004477114845],"iteration":391,"passed_time":61.24859051,"remaining_time":46.09268929},
{"learn":[0.0004477114845],"iteration":392,"passed_time":61.64971651,"remaining_time":46.11963525},
{"learn":[0.0004477114845],"iteration":393,"passed_time":61.91445751,"remaining_time":46.0429849},
{"learn":[0.0004477073831],"iteration":394,"passed_time":62.08128155,"remaining_time":45.89299801},
{"learn":[0.0004477073831],"iteration":395,"passed_time":62.54097353,"remaining_time":45.95813964},
{"learn":[0.0004477073831],"iteration":396,"passed_time":62.73686554,"remaining_time":45.82793704},
{"learn":[0.0004477073831],"iteration":397,"passed_time":62.89518276,"remaining_time":45.67012014},
{"learn":[0.0004477073831],"iteration":398,"passed_time":63.02746407,"remaining_time":45.4935079},
{"learn":[0.0004477042624],"iteration":399,"passed_time":63.21575108,"remaining_time":45.3573014},
{"learn":[0.0004477042624],"iteration":400,"passed_time":63.39263019,"remaining_time":45.21269884},
{"learn":[0.0004477042624],"iteration":401,"passed_time":63.65807411,"remaining_time":45.13072418},
{"learn":[0.0004477042624],"iteration":402,"passed_time":63.88345998,"remaining_time":45.01960952},
{"learn":[0.0004477042624],"iteration":403,"passed_time":64.11893509,"remaining_time":44.91499661},
{"learn":[0.0004477042624],"iteration":404,"passed_time":64.38530644,"remaining_time":44.83125041},
{"learn":[0.0004477042624],"iteration":405,"passed_time":64.7118158,"remaining_time":44.78822719},
{"learn":[0.0004477042624],"iteration":406,"passed_time":64.88353104,"remaining_time":44.63731865},
{"learn":[0.0004477042624],"iteration":407,"passed_time":65.00949484,"remaining_time":44.45502221},
{"learn":[0.0004477042624],"iteration":408,"passed_time":65.19028248,"remaining_time":44.31026535},
{"learn":[0.0004477042624],"iteration":409,"passed_time":65.32224363,"remaining_time":44.13234509},
{"learn":[0.0004477042624],"iteration":410,"passed_time":65.47839588,"remaining_time":43.97089359},
{"learn":[0.0004477042624],"iteration":411,"passed_time":65.61942215,"remaining_time":43.79937158},
{"learn":[0.0004477042624],"iteration":412,"passed_time":65.76198193,"remaining_time":43.62901464},
{"learn":[0.0004477042624],"iteration":413,"passed_time":65.89038369,"remaining_time":43.44945591},
{"learn":[0.0004477270878],"iteration":414,"passed_time":66.01705902,"remaining_time":43.26901218},
{"learn":[0.0004477270878],"iteration":415,"passed_time":66.15723905,"remaining_time":43.09762448},
{"learn":[0.0004477270878],"iteration":416,"passed_time":66.31767296,"remaining_time":42.93950048},
{"learn":[0.0004477270878],"iteration":417,"passed_time":66.47708907,"remaining_time":42.78071043},
{"learn":[0.0004477270878],"iteration":418,"passed_time":66.62409604,"remaining_time":42.61398029},
{"learn":[0.0004477270878],"iteration":419,"passed_time":66.75984017,"remaining_time":42.44018411},
{"learn":[0.0004477270878],"iteration":420,"passed_time":66.90301995,"remaining_time":42.27126676},
{"learn":[0.0004477270878],"iteration":421,"passed_time":67.02784748,"remaining_time":42.09094687},
{"learn":[0.0004477270878],"iteration":422,"passed_time":67.16746897,"remaining_time":41.92012248},
{"learn":[0.0004477270878],"iteration":423,"passed_time":67.29903446,"remaining_time":41.74444826},
{"learn":[0.0004477270878],"iteration":424,"passed_time":67.42799566,"remaining_time":41.56737615},
{"learn":[0.0004477279794],"iteration":425,"passed_time":67.62872696,"remaining_time":41.43450173},
{"learn":[0.0004477279794],"iteration":426,"passed_time":67.83107681,"remaining_time":41.30229501},
{"learn":[0.0004477279794],"iteration":427,"passed_time":67.96827159,"remaining_time":41.13033258},
{"learn":[0.0004477279794],"iteration":428,"passed_time":68.20397362,"remaining_time":41.01777435},
{"learn":[0.0004477279794],"iteration":429,"passed_time":68.37357318,"remaining_time":40.8651356},
{"learn":[0.0004477279794],"iteration":430,"passed_time":68.49922151,"remaining_time":40.68631254},
{"learn":[0.0004477279794],"iteration":431,"passed_time":68.6254305,"remaining_time":40.50806661},
{"learn":[0.0004477279794],"iteration":432,"passed_time":68.74951524,"remaining_time":40.32881494},
{"learn":[0.0004477279794],"iteration":433,"passed_time":68.87552355,"remaining_time":40.15093884},
{"learn":[0.0004477279794],"iteration":434,"passed_time":69.00074762,"remaining_time":39.9728469},
{"learn":[0.0004477279794],"iteration":435,"passed_time":69.12521837,"remaining_time":39.79456379},
{"learn":[0.0004477279794],"iteration":436,"passed_time":69.27055086,"remaining_time":39.62846159},
{"learn":[0.0004477279794],"iteration":437,"passed_time":69.3970058,"remaining_time":39.45172248},
{"learn":[0.0004477279794],"iteration":438,"passed_time":69.5218505,"remaining_time":39.27430279},
{"learn":[0.0004477279794],"iteration":439,"passed_time":69.64731828,"remaining_time":39.09747186},
{"learn":[0.0004477279794],"iteration":440,"passed_time":69.77840658,"remaining_time":38.92400911},
{"learn":[0.0004477279794],"iteration":441,"passed_time":69.91510111,"remaining_time":38.75384564},
{"learn":[0.0004477279794],"iteration":442,"passed_time":70.04630799,"remaining_time":38.58081072},
{"learn":[0.0004477279794],"iteration":443,"passed_time":70.17971294,"remaining_time":38.40916722},
{"learn":[0.0004477279794],"iteration":444,"passed_time":70.31162336,"remaining_time":38.23688282},
{"learn":[0.0004477279794],"iteration":445,"passed_time":70.44588883,"remaining_time":38.06605203},
{"learn":[0.0004477279794],"iteration":446,"passed_time":70.57700149,"remaining_time":37.89369208},
{"learn":[0.0004477279794],"iteration":447,"passed_time":70.73388592,"remaining_time":37.73526503},
{"learn":[0.0004477279794],"iteration":448,"passed_time":70.85887116,"remaining_time":37.55993616},
{"learn":[0.0004477279794],"iteration":449,"passed_time":71.00454619,"remaining_time":37.39572766},
{"learn":[0.0004477279794],"iteration":450,"passed_time":71.14730021,"remaining_time":37.23007284},
{"learn":[0.0004477279794],"iteration":451,"passed_time":71.29837126,"remaining_time":37.06884347},
{"learn":[0.0004477279794],"iteration":452,"passed_time":71.51428618,"remaining_time":36.94115445},
{"learn":[0.0004477279794],"iteration":453,"passed_time":71.6462669,"remaining_time":36.77000042},
{"learn":[0.0004477279794],"iteration":454,"passed_time":71.77027656,"remaining_time":36.5949542},
{"learn":[0.0004477279794],"iteration":455,"passed_time":71.90218451,"remaining_time":36.42413294},
{"learn":[0.0004477279794],"iteration":456,"passed_time":72.03520409,"remaining_time":36.25404145},
{"learn":[0.0004477279794],"iteration":457,"passed_time":72.16873192,"remaining_time":36.08436596},
{"learn":[0.0004477279794],"iteration":458,"passed_time":72.30632207,"remaining_time":35.91686587},
{"learn":[0.0004477279794],"iteration":459,"passed_time":72.436322,"remaining_time":35.74575021},
{"learn":[0.0004477279794],"iteration":460,"passed_time":72.56401701,"remaining_time":35.57368296},
{"learn":[0.0004477279794],"iteration":461,"passed_time":72.69240067,"remaining_time":35.40214318},
{"learn":[0.0004477279794],"iteration":462,"passed_time":72.81956217,"remaining_time":35.23019854},
{"learn":[0.0004477279794],"iteration":463,"passed_time":72.97274783,"remaining_time":35.07095424},
{"learn":[0.0004477279794],"iteration":464,"passed_time":73.104685,"remaining_time":34.90159155},
{"learn":[0.0004477279794],"iteration":465,"passed_time":73.24366268,"remaining_time":34.73572844},
{"learn":[0.0004477279794],"iteration":466,"passed_time":73.40999695,"remaining_time":34.58286794},
{"learn":[0.0004477279794],"iteration":467,"passed_time":73.53908238,"remaining_time":34.41251932},
{"learn":[0.0004477279794],"iteration":468,"passed_time":73.66578691,"remaining_time":34.24123997},
{"learn":[0.0004477279794],"iteration":469,"passed_time":73.80212817,"remaining_time":34.0745996},
{"learn":[0.0004477279794],"iteration":470,"passed_time":73.92557877,"remaining_time":33.90217625},
{"learn":[0.0004477279794],"iteration":471,"passed_time":74.04834889,"remaining_time":33.72965045},
{"learn":[0.0004477109495],"iteration":472,"passed_time":74.17832175,"remaining_time":33.56059377},
{"learn":[0.0004477109495],"iteration":473,"passed_time":74.31433823,"remaining_time":33.39441781},
{"learn":[0.0004477109495],"iteration":474,"passed_time":74.44085426,"remaining_time":33.22412864},
{"learn":[0.0004477109495],"iteration":475,"passed_time":74.57263581,"remaining_time":33.05635747},
{"learn":[0.0004477109495],"iteration":476,"passed_time":74.74820899,"remaining_time":32.90801654},
{"learn":[0.0004477109495],"iteration":477,"passed_time":74.9178104,"remaining_time":32.75695057},
{"learn":[0.0004477109495],"iteration":478,"passed_time":75.04115052,"remaining_time":32.58571881},
{"learn":[0.0004477109495],"iteration":479,"passed_time":75.17142059,"remaining_time":32.41767513},
{"learn":[0.0004477109495],"iteration":480,"passed_time":75.31098016,"remaining_time":32.25376697},
{"learn":[0.0004477109495],"iteration":481,"passed_time":75.43418165,"remaining_time":32.08300257},
{"learn":[0.0004477109495],"iteration":482,"passed_time":75.56327588,"remaining_time":31.91492397},
{"learn":[0.0004476965053],"iteration":483,"passed_time":75.69213681,"remaining_time":31.74690862},
{"learn":[0.0004476965053],"iteration":484,"passed_time":75.81518503,"remaining_time":31.57663376},
{"learn":[0.0004476965053],"iteration":485,"passed_time":75.94525786,"remaining_time":31.4094585},
{"learn":[0.0004476965053],"iteration":486,"passed_time":76.06843858,"remaining_time":31.23960517},
{"learn":[0.0004476965053],"iteration":487,"passed_time":76.22730607,"remaining_time":31.08449571},
{"learn":[0.0004476965053],"iteration":488,"passed_time":76.38508089,"remaining_time":30.92892846},
{"learn":[0.0004476965053],"iteration":489,"passed_time":76.53617375,"remaining_time":30.77066577},
{"learn":[0.0004476965053],"iteration":490,"passed_time":76.69057828,"remaining_time":30.61375426},
{"learn":[0.0004476965053],"iteration":491,"passed_time":76.8401075,"remaining_time":30.45492066},
{"learn":[0.0004476965053],"iteration":492,"passed_time":76.97072986,"remaining_time":30.28868477},
{"learn":[0.0004476965053],"iteration":493,"passed_time":77.09305958,"remaining_time":30.11935324},
{"learn":[0.0004476965053],"iteration":494,"passed_time":77.22548364,"remaining_time":29.95412699},
{"learn":[0.0004476965053],"iteration":495,"passed_time":77.36055605,"remaining_time":29.79005283},
{"learn":[0.0004476965053],"iteration":496,"passed_time":77.48499362,"remaining_time":29.62202975},
{"learn":[0.0004476965053],"iteration":497,"passed_time":77.61348003,"remaining_time":29.45571832},
{"learn":[0.0004476965053],"iteration":498,"passed_time":77.75371381,"remaining_time":29.29398436},
{"learn":[0.0004358857803],"iteration":499,"passed_time":77.99490314,"remaining_time":29.17009378},
{"learn":[0.0004358857803],"iteration":500,"passed_time":78.26533868,"remaining_time":29.0565928},
{"learn":[0.0004358857803],"iteration":501,"passed_time":78.50132763,"remaining_time":28.92977214},
{"learn":[0.0004358857803],"iteration":502,"passed_time":78.6370761,"remaining_time":28.76584891},
{"learn":[0.0004358857803],"iteration":503,"passed_time":78.76125962,"remaining_time":28.59783832},
{"learn":[0.0004358857803],"iteration":504,"passed_time":78.89046892,"remaining_time":28.43181256},
{"learn":[0.0004358857803],"iteration":505,"passed_time":79.02133712,"remaining_time":28.26652573},
{"learn":[0.0004358857803],"iteration":506,"passed_time":79.16153845,"remaining_time":28.10468821},
{"learn":[0.0004358857803],"iteration":507,"passed_time":79.30345954,"remaining_time":27.94354184},
{"learn":[0.0004358857803],"iteration":508,"passed_time":79.44059147,"remaining_time":27.78079623},
{"learn":[0.0004358857803],"iteration":509,"passed_time":79.56779532,"remaining_time":27.61470544},
{"learn":[0.0004358857803],"iteration":510,"passed_time":79.68993617,"remaining_time":27.44702303},
{"learn":[0.0004358857803],"iteration":511,"passed_time":79.82780598,"remaining_time":27.28489462},
{"learn":[0.0004358857803],"iteration":512,"passed_time":79.95272969,"remaining_time":27.11846972},
{"learn":[0.0004358857803],"iteration":513,"passed_time":80.08498728,"remaining_time":26.95467471},
{"learn":[0.0004358857803],"iteration":514,"passed_time":80.20863225,"remaining_time":26.78812572},
{"learn":[0.0004358857803],"iteration":515,"passed_time":80.35681325,"remaining_time":26.62987416},
{"learn":[0.0004358857803],"iteration":516,"passed_time":80.48314945,"remaining_time":26.46447854},
{"learn":[0.0004358857803],"iteration":517,"passed_time":80.61157921,"remaining_time":26.29991677},
{"learn":[0.0004359191714],"iteration":518,"passed_time":80.74006753,"remaining_time":26.13551319},
{"learn":[0.0004359191714],"iteration":519,"passed_time":80.87573865,"remaining_time":25.97355453},
{"learn":[0.0004359191714],"iteration":520,"passed_time":81.00244837,"remaining_time":25.80884151},
{"learn":[0.0004359191714],"iteration":521,"passed_time":81.12860382,"remaining_time":25.64409891},
{"learn":[0.0004359191714],"iteration":522,"passed_time":81.26481677,"remaining_time":25.48265765},
{"learn":[0.0004359191714],"iteration":523,"passed_time":81.40313663,"remaining_time":25.32196807},
{"learn":[0.0004359191714],"iteration":524,"passed_time":81.62041916,"remaining_time":25.18572934},
{"learn":[0.0004359191714],"iteration":525,"passed_time":81.76855987,"remaining_time":25.02801928},
{"learn":[0.0004359191714],"iteration":526,"passed_time":81.91578134,"remaining_time":24.87006644},
{"learn":[0.0004359191714],"iteration":527,"passed_time":82.05350962,"remaining_time":24.70929551},
{"learn":[0.0004359191714],"iteration":528,"passed_time":82.19938654,"remaining_time":24.55104551},
{"learn":[0.0004359191714],"iteration":529,"passed_time":82.35955153,"remaining_time":24.3970747},
{"learn":[0.0004359191714],"iteration":530,"passed_time":82.49750283,"remaining_time":24.2365545},
{"learn":[0.0004359191714],"iteration":531,"passed_time":82.62021942,"remaining_time":24.07168047},
{"learn":[0.0004359191714],"iteration":532,"passed_time":82.7516271,"remaining_time":23.90947575},
{"learn":[0.0004359191714],"iteration":533,"passed_time":82.88612894,"remaining_time":23.7482729},
{"learn":[0.0004359191714],"iteration":534,"passed_time":83.04836421,"remaining_time":23.59504927},
{"learn":[0.0004359191714],"iteration":535,"passed_time":83.1753529,"remaining_time":23.43186248},
{"learn":[0.0004359191714],"iteration":536,"passed_time":83.31443164,"remaining_time":23.27218761},
{"learn":[0.0004359191714],"iteration":537,"passed_time":83.44702901,"remaining_time":23.11079428},
{"learn":[0.0004359191714],"iteration":538,"passed_time":83.61955361,"remaining_time":22.96047112},
{"learn":[0.0004359191714],"iteration":539,"passed_time":83.7438935,"remaining_time":22.79694879},
{"learn":[0.0004359191714],"iteration":540,"passed_time":83.87595817,"remaining_time":22.635656},
{"learn":[0.0004359191714],"iteration":541,"passed_time":84.0077466,"remaining_time":22.47439715},
{"learn":[0.0004359191714],"iteration":542,"passed_time":84.14216686,"remaining_time":22.3139448},
{"learn":[0.0004359191714],"iteration":543,"passed_time":84.27456897,"remaining_time":22.15305765},
{"learn":[0.0004359191714],"iteration":544,"passed_time":84.40359077,"remaining_time":21.99139429},
{"learn":[0.0004359191714],"iteration":545,"passed_time":84.54196437,"remaining_time":21.83226553},
{"learn":[0.0004359191714],"iteration":546,"passed_time":84.66489782,"remaining_time":21.66926087},
{"learn":[0.0004359191714],"iteration":547,"passed_time":84.85726806,"remaining_time":21.52401507},
{"learn":[0.0004359191714],"iteration":548,"passed_time":85.01066427,"remaining_time":21.36880085},
{"learn":[0.0004359191714],"iteration":549,"passed_time":85.14025435,"remaining_time":21.20766336},
{"learn":[0.0004359191714],"iteration":550,"passed_time":85.28015691,"remaining_time":21.04918573},
{"learn":[0.0004359191714],"iteration":551,"passed_time":85.40207372,"remaining_time":20.88637672},
{"learn":[0.0004359191714],"iteration":552,"passed_time":85.54010488,"remaining_time":20.72762035},
{"learn":[0.0004359071791],"iteration":553,"passed_time":85.6711876,"remaining_time":20.56727067},
{"learn":[0.0004359071791],"iteration":554,"passed_time":85.80066483,"remaining_time":20.40664461},
{"learn":[0.0004359071791],"iteration":555,"passed_time":85.92313817,"remaining_time":20.2444804},
{"learn":[0.0004359071791],"iteration":556,"passed_time":86.08004344,"remaining_time":20.09049488},
{"learn":[0.0004359071791],"iteration":557,"passed_time":86.21940303,"remaining_time":19.93244264},
{"learn":[0.0004359071791],"iteration":558,"passed_time":86.35270893,"remaining_time":19.7730711},
{"learn":[0.0004359071791],"iteration":559,"passed_time":86.48906293,"remaining_time":19.61448392},
{"learn":[0.0004359071791],"iteration":560,"passed_time":86.63108124,"remaining_time":19.45724819},
{"learn":[0.0004359071791],"iteration":561,"passed_time":86.77304543,"remaining_time":19.30005459},
{"learn":[0.0004359071791],"iteration":562,"passed_time":86.89852197,"remaining_time":19.1392837},
{"learn":[0.0004359071791],"iteration":563,"passed_time":87.02428567,"remaining_time":18.9787006},
{"learn":[0.0004359071791],"iteration":564,"passed_time":87.16106369,"remaining_time":18.82061906},
{"learn":[0.0004359071791],"iteration":565,"passed_time":87.31486016,"remaining_time":18.66625102},
{"learn":[0.0004359071791],"iteration":566,"passed_time":87.47794541,"remaining_time":18.51385088},
{"learn":[0.0004359071791],"iteration":567,"passed_time":87.65806937,"remaining_time":18.36498284},
{"learn":[0.0004359071791],"iteration":568,"passed_time":87.79609401,"remaining_time":18.20727433},
{"learn":[0.0004359071791],"iteration":569,"passed_time":87.98059155,"remaining_time":18.05917405},
{"learn":[0.0004359071791],"iteration":570,"passed_time":88.1949702,"remaining_time":17.91701671},
{"learn":[0.0004359071791],"iteration":571,"passed_time":88.53078296,"remaining_time":17.79902105},
{"learn":[0.0004359071791],"iteration":572,"passed_time":88.71831151,"remaining_time":17.65076355},
{"learn":[0.0004359071791],"iteration":573,"passed_time":88.84598623,"remaining_time":17.49058614},
{"learn":[0.0004359071791],"iteration":574,"passed_time":88.97959364,"remaining_time":17.33167737},
{"learn":[0.0004359071791],"iteration":575,"passed_time":89.10720342,"remaining_time":17.17170066},
{"learn":[0.0004359071791],"iteration":576,"passed_time":89.23305427,"remaining_time":17.01150081},
{"learn":[0.0004359071791],"iteration":577,"passed_time":89.37213945,"remaining_time":16.85391557},
{"learn":[0.0004359071791],"iteration":578,"passed_time":89.50538803,"remaining_time":16.69530554},
{"learn":[0.0004359071791],"iteration":579,"passed_time":89.62812647,"remaining_time":16.53484402},
{"learn":[0.0004359071791],"iteration":580,"passed_time":89.75896228,"remaining_time":16.37598968},
{"learn":[0.0004358983967],"iteration":581,"passed_time":89.88420453,"remaining_time":16.21622247},
{"learn":[0.0004358983967],"iteration":582,"passed_time":90.02015246,"remaining_time":16.05848346},
{"learn":[0.0004358983967],"iteration":583,"passed_time":90.14549886,"remaining_time":15.89894929},
{"learn":[0.0004358983967],"iteration":584,"passed_time":90.28175379,"remaining_time":15.74143399},
{"learn":[0.0004358983967],"iteration":585,"passed_time":90.40765939,"remaining_time":15.58220751},
{"learn":[0.0004358983967],"iteration":586,"passed_time":90.54477055,"remaining_time":15.4250035},
{"learn":[0.0004358983967],"iteration":587,"passed_time":90.66863875,"remaining_time":15.26563816},
{"learn":[0.0004358983967],"iteration":588,"passed_time":90.80047517,"remaining_time":15.10771913},
{"learn":[0.0004358983967],"iteration":589,"passed_time":90.92705923,"remaining_time":14.94902499},
{"learn":[0.0004358983967],"iteration":590,"passed_time":91.05756597,"remaining_time":14.79107671},
{"learn":[0.0004358983967],"iteration":591,"passed_time":91.18931927,"remaining_time":14.63342117},
{"learn":[0.0004359009378],"iteration":592,"passed_time":91.32198016,"remaining_time":14.47599685},
{"learn":[0.0004359009378],"iteration":593,"passed_time":91.44817314,"remaining_time":14.31764327},
{"learn":[0.0004358844429],"iteration":594,"passed_time":91.5834435,"remaining_time":14.16080135},
{"learn":[0.0004358844429],"iteration":595,"passed_time":91.72665631,"remaining_time":14.0052445},
{"learn":[0.0004358611717],"iteration":596,"passed_time":91.92666013,"remaining_time":13.85829047},
{"learn":[0.0004358611717],"iteration":597,"passed_time":92.05236074,"remaining_time":13.70010051},
{"learn":[0.0004358611717],"iteration":598,"passed_time":92.18815516,"remaining_time":13.54350193},
{"learn":[0.0004358611717],"iteration":599,"passed_time":92.32078489,"remaining_time":13.38651381},
{"learn":[0.0004358611717],"iteration":600,"passed_time":92.45127245,"remaining_time":13.22930022},
{"learn":[0.0004358611717],"iteration":601,"passed_time":92.58778908,"remaining_time":13.0730267},
{"learn":[0.0004358611717],"iteration":602,"passed_time":92.7181092,"remaining_time":12.91595551},
{"learn":[0.0004358611717],"iteration":603,"passed_time":92.84269599,"remaining_time":12.75818505},
{"learn":[0.0004358611717],"iteration":604,"passed_time":93.0131845,"remaining_time":12.60674567},
{"learn":[0.0004358611717],"iteration":605,"passed_time":93.17522772,"remaining_time":12.4541146},
{"learn":[0.0004358714253],"iteration":606,"passed_time":93.35502813,"remaining_time":12.30379283},
{"learn":[0.0004358714253],"iteration":607,"passed_time":93.51084549,"remaining_time":12.15025788},
{"learn":[0.0004358714253],"iteration":608,"passed_time":93.65100447,"remaining_time":11.99470993},
{"learn":[0.0004358702662],"iteration":609,"passed_time":93.8232863,"remaining_time":11.84326729},
{"learn":[0.0004358702662],"iteration":610,"passed_time":93.94661211,"remaining_time":11.68566697},
{"learn":[0.0004358702662],"iteration":611,"passed_time":94.074376,"remaining_time":11.52872255},
{"learn":[0.0004358702662],"iteration":612,"passed_time":94.20220501,"remaining_time":11.37188119},
{"learn":[0.0004358702662],"iteration":613,"passed_time":94.3345771,"remaining_time":11.21567448},
{"learn":[0.0004358702662],"iteration":614,"passed_time":94.46530692,"remaining_time":11.05935301},
{"learn":[0.0004358702662],"iteration":615,"passed_time":94.59790233,"remaining_time":10.90332965},
{"learn":[0.0004358702662],"iteration":616,"passed_time":94.72268495,"remaining_time":10.74649586},
{"learn":[0.0004358702662],"iteration":617,"passed_time":94.85237323,"remaining_time":10.59031352},
{"learn":[0.0004358702662],"iteration":618,"passed_time":95.10833246,"remaining_time":10.44808822},
{"learn":[0.0004358702662],"iteration":619,"passed_time":95.29421854,"remaining_time":10.29792362},
{"learn":[0.0004358702662],"iteration":620,"passed_time":95.41952093,"remaining_time":10.14120512},
{"learn":[0.0004358702662],"iteration":621,"passed_time":95.55217196,"remaining_time":9.985355591},
{"learn":[0.0004358702662],"iteration":622,"passed_time":95.78495342,"remaining_time":9.839866804},
{"learn":[0.0004358702662],"iteration":623,"passed_time":95.90670635,"remaining_time":9.682888622},
{"learn":[0.0004358702662],"iteration":624,"passed_time":96.0313745,"remaining_time":9.52631235},
{"learn":[0.0004358702662],"iteration":625,"passed_time":96.16645677,"remaining_time":9.370852816},
{"learn":[0.0004358702662],"iteration":626,"passed_time":96.30311241,"remaining_time":9.215608844},
{"learn":[0.0004358702662],"iteration":627,"passed_time":96.45102503,"remaining_time":9.06148165},
{"learn":[0.0004358702662],"iteration":628,"passed_time":96.58819747,"remaining_time":8.906383869},
{"learn":[0.0004358702662],"iteration":629,"passed_time":96.74755514,"remaining_time":8.753350227},
{"learn":[0.0004358702662],"iteration":630,"passed_time":96.87246286,"remaining_time":8.597239177},
{"learn":[0.0004358702662],"iteration":631,"passed_time":96.99824365,"remaining_time":8.44130285},
{"learn":[0.0004358702662],"iteration":632,"passed_time":97.13047542,"remaining_time":8.286012121},
{"learn":[0.0004358702662],"iteration":633,"passed_time":97.26886377,"remaining_time":8.131308801},
{"learn":[0.0004358702662],"iteration":634,"passed_time":97.40312259,"remaining_time":7.9763187},
{"learn":[0.0004358702662],"iteration":635,"passed_time":97.54618259,"remaining_time":7.822099547},
{"learn":[0.0004358702662],"iteration":636,"passed_time":97.70130892,"remaining_time":7.668862552},
{"learn":[0.0004358702662],"iteration":637,"passed_time":97.83182629,"remaining_time":7.513729606},
{"learn":[0.0004358702662],"iteration":638,"passed_time":97.96857586,"remaining_time":7.359141849},
{"learn":[0.0004358702662],"iteration":639,"passed_time":98.1007699,"remaining_time":7.20427529},
{"learn":[0.0004358702662],"iteration":640,"passed_time":98.27296122,"remaining_time":7.052349791},
{"learn":[0.0004358514976],"iteration":641,"passed_time":98.75965489,"remaining_time":6.922405717},
{"learn":[0.0004358514976],"iteration":642,"passed_time":99.13946886,"remaining_time":6.784038305},
{"learn":[0.0004358514976],"iteration":643,"passed_time":99.48041544,"remaining_time":6.642325876},
{"learn":[0.0004358514976],"iteration":644,"passed_time":99.79993421,"remaining_time":6.498600367},
{"learn":[0.0004358514976],"iteration":645,"passed_time":100.0832012,"remaining_time":6.352029796},
{"learn":[0.0004358514976],"iteration":646,"passed_time":100.2109944,"remaining_time":6.19542469},
{"learn":[0.0004358514976],"iteration":647,"passed_time":100.3439988,"remaining_time":6.039222153},
{"learn":[0.0004358514976],"iteration":648,"passed_time":100.4703444,"remaining_time":5.882701211},
{"learn":[0.0004358514976],"iteration":649,"passed_time":100.6063115,"remaining_time":5.726820808},
{"learn":[0.0004358514976],"iteration":650,"passed_time":100.8553906,"remaining_time":5.577256623}
]}